ShynaBot/__init__.py
ShynaBot/speak_Shyna_bot_handler.py
ShynaBot/speak_shyna_intro_adapter.py
ShynaBot-0.0.1.dist-info/LICENSE
ShynaBot-0.0.1.dist-info/METADATA
ShynaBot-0.0.1.dist-info/WHEEL
ShynaBot-0.0.1.dist-info/top_level.txt
ShynaBot-0.0.1.dist-info/RECORD
