Metadata-Version: 2.1
Name: ShynaBot
Version: 0.0.1
Summary: Shyna Bot For App integration.BASIC META
Author: Shivam Sharma
Author-email: shivamsharma1913@gmail.com
License-File: LICENSE
Requires-Dist: setuptools
Requires-Dist: wheel
Requires-Dist: wget
Requires-Dist: chatterbot ==1.0.4
Requires-Dist: requests
